<?xml version="1.0" encoding="UTF-8"?>
<db:article xmlns:db="http://docbook.org/ns/docbook" xmlns:xlink="http://www.w3.org/1999/xlink" version="5.2" xml:lang="en_US">
<db:info>
<db:title>Context Commands</db:title>
<db:productname>QDoc</db:productname>
<db:titleabbrev>QDoc Manual</db:titleabbrev>
<db:extendedlink xlink:type="extended"><db:link xlink:to="13-qdoc-commands-topics.xml" xlink:type="arc" xlink:arcrole="prev" xlink:title="Topic Commands"/></db:extendedlink>
<db:extendedlink xlink:type="extended"><db:link xlink:to="15-qdoc-commands-navigation.xml" xlink:type="arc" xlink:arcrole="next" xlink:title="Document Navigation"/></db:extendedlink>
<db:abstract>
<db:para>QDoc Manual.</db:para></db:abstract>
<db:pubdate>2025-06-29</db:pubdate>
<db:date>2025-06-29</db:date>
<db:authorgroup>
<db:author>
<db:orgname class="corporation">The Qt Company Ltd.</db:orgname>
</db:author>
</db:authorgroup>
</db:info>
<db:para><db:emphasis role="bold">&lt;Unknown command&gt;<db:code>contentspage</db:code></db:emphasis>QDoc Manual</db:para>
<db:para>The context commands provide information about the element being documented that QDoc can't deduce on its own. e.g. Is a class thread-safe? Is a function reentrant? Which module is the class a member of? Context commands can appear anywhere in a QDoc comment, but they are normally placed near the top of the comment, just below the <db:link xlink:href="13-qdoc-commands-topics.xml">topic</db:link> command.</db:para>
<db:itemizedlist>
<db:listitem>
<db:para><db:link xlink:href="16-qdoc-commands-status.xml#compat">\compat</db:link>,</db:para>
</db:listitem>
<db:listitem>
<db:para><db:link xlink:href="15-qdoc-commands-navigation.xml#contentspage">\contentspage</db:link>,</db:para>
</db:listitem>
<db:listitem>
<db:para><db:link xlink:href="15-qdoc-commands-navigation.xml#indexpage">\indexpage</db:link>,</db:para>
</db:listitem>
<db:listitem>
<db:para><db:link xlink:href="19-qdoc-commands-grouping.xml#ingroup">\ingroup</db:link>,</db:para>
</db:listitem>
<db:listitem>
<db:para><db:link xlink:href="18-qdoc-commands-relating.xml#inherits">\inherits</db:link>,</db:para>
</db:listitem>
<db:listitem>
<db:para><db:link xlink:href="19-qdoc-commands-grouping.xml#inmodule">\inmodule</db:link>,</db:para>
</db:listitem>
<db:listitem>
<db:para><db:link xlink:href="16-qdoc-commands-status.xml#internal">\internal</db:link>,</db:para>
</db:listitem>
<db:listitem>
<db:para><db:link xlink:href="19-qdoc-commands-grouping.xml#mainclass">\mainclass</db:link>,</db:para>
</db:listitem>
<db:listitem>
<db:para><db:link xlink:href="15-qdoc-commands-navigation.xml#nextpage">\nextpage</db:link>,</db:para>
</db:listitem>
<db:listitem>
<db:para><db:link xlink:href="17-qdoc-commands-thread.xml#nonreentrant">\nonreentrant</db:link>,</db:para>
</db:listitem>
<db:listitem>
<db:para><db:link xlink:href="16-qdoc-commands-status.xml#obsolete">\obsolete</db:link>,</db:para>
</db:listitem>
<db:listitem>
<db:para><db:link xlink:href="18-qdoc-commands-relating.xml#overload">\overload</db:link>,</db:para>
</db:listitem>
<db:listitem>
<db:para><db:link xlink:href="16-qdoc-commands-status.xml#preliminary">\preliminary</db:link>,</db:para>
</db:listitem>
<db:listitem>
<db:para><db:link xlink:href="15-qdoc-commands-navigation.xml#previouspage">\previouspage</db:link>,</db:para>
</db:listitem>
<db:listitem>
<db:para><db:link xlink:href="17-qdoc-commands-thread.xml#reentrant">\reentrant</db:link>,</db:para>
</db:listitem>
<db:listitem>
<db:para><db:link xlink:href="18-qdoc-commands-relating.xml#reimp">\reimp</db:link>,</db:para>
</db:listitem>
<db:listitem>
<db:para><db:link xlink:href="18-qdoc-commands-relating.xml#relates">\relates</db:link>,</db:para>
</db:listitem>
<db:listitem>
<db:para><db:link xlink:href="16-qdoc-commands-status.xml#since">\since</db:link>,</db:para>
</db:listitem>
<db:listitem>
<db:para><db:link xlink:href="15-qdoc-commands-navigation.xml#startpage">\startpage</db:link>,</db:para>
</db:listitem>
<db:listitem>
<db:para><db:link xlink:href="20-qdoc-commands-namingthings.xml#subtitle">\subtitle</db:link></db:para>
</db:listitem>
<db:listitem>
<db:para><db:link xlink:href="17-qdoc-commands-thread.xml#threadsafe">\threadsafe</db:link>,</db:para>
</db:listitem>
<db:listitem>
<db:para><db:link xlink:href="20-qdoc-commands-namingthings.xml#title">\title</db:link></db:para>
</db:listitem>
</db:itemizedlist>
</db:article>
