<?xml version="1.0" encoding="UTF-8"?>
<db:article xmlns:db="http://docbook.org/ns/docbook" xmlns:xlink="http://www.w3.org/1999/xlink" version="5.2" xml:lang="en">
<db:info>
<db:title>Wrapper Example (ActiveQt)</db:title>
<db:productname>ActiveQt</db:productname>
<db:edition>Qt 5.6.3 Reference Documentation</db:edition>
<db:titleabbrev>ActiveQt</db:titleabbrev>
<db:abstract>
<db:para>The Wrapper example demonstrates how to export existing <db:link xlink:href="qwidget.xml">QWidget</db:link> classes as ActiveX controls, and the use of <db:link xlink:href="qaxfactory.xml">QAxFactory</db:link> together with the <db:code>QAXFACTORY_EXPORT()</db:code> macro. ActiveX controls in this example are the standard button classes <db:link xlink:href="qpushbutton.xml">QPushButton</db:link>, <db:link xlink:href="qcheckbox.xml">QCheckBox</db:link> and <db:link xlink:href="qradiobutton.xml">QRadioButton</db:link> as provided by Qt.</db:para>
</db:abstract>
<db:pubdate>2025-06-29</db:pubdate>
<db:date>2025-06-29</db:date>
<db:authorgroup>
<db:author>
<db:orgname class="corporation">The Qt Company Ltd.</db:orgname>
</db:author>
</db:authorgroup>
</db:info>
<db:programlisting language="cpp">include(../shared.pri)

TEMPLATE = lib
TARGET   = wrapperax

CONFIG += warn_off dll
QT += widgets axserver

SOURCES  = main.cpp
RC_FILE  = wrapperax.rc
DEF_FILE = wrapperax.def

# install
target.path = $$[QT_INSTALL_EXAMPLES]/activeqt/wrapper
INSTALLS += target

</db:programlisting>
</db:article>
