<?xml version="1.0" encoding="UTF-8"?>
<db:article xmlns:db="http://docbook.org/ns/docbook" xmlns:xlink="http://www.w3.org/1999/xlink" version="5.2" xml:lang="en">
<db:info>
<db:title>All QML Modules</db:title>
<db:productname>QtDoc</db:productname>
<db:edition>Qt 6.4.3 Reference Documentation</db:edition>
<db:titleabbrev>Qt Reference Documentation</db:titleabbrev>
<db:abstract>
<db:para>A list of all QML modules in Qt.</db:para>
</db:abstract>
<db:pubdate>2024-01-26</db:pubdate>
<db:date>2024-01-26</db:date>
<db:authorgroup>
<db:author>
<db:orgname class="corporation">The Qt Company Ltd.</db:orgname>
</db:author>
</db:authorgroup>
</db:info>
<db:para>These are the QML API pages for Qt's QML modules.</db:para>
<db:variablelist role="qml-modules">
<db:varlistentry>
<db:term><db:link xlink:href="qt3d-core-qmlmodule.xml" xlink:role="">Qt 3D Core QML Types</db:link></db:term>
<db:listitem>
<db:para>Provides core Qt 3D QML types.</db:para>
</db:listitem>
</db:varlistentry>
<db:varlistentry>
<db:term><db:link xlink:href="qt3d-extras-qmlmodule.xml" xlink:role="">Qt 3D Extras QML Types</db:link></db:term>
<db:listitem>
<db:para>Provides Qt 3D QML types for the extras module.</db:para>
</db:listitem>
</db:varlistentry>
<db:varlistentry>
<db:term><db:link xlink:href="qt3d-input-qmlmodule.xml" xlink:role="">Qt 3D Input QML Types</db:link></db:term>
<db:listitem>
<db:para>Provides QML types for Qt 3D user input.</db:para>
</db:listitem>
</db:varlistentry>
<db:varlistentry>
<db:term><db:link xlink:href="qt3d-logic-qmlmodule.xml" xlink:role="">Qt 3D Logic QML Types</db:link></db:term>
<db:listitem>
<db:para>Provides QML types to synchronize frames with the 3D backend.</db:para>
</db:listitem>
</db:varlistentry>
<db:varlistentry>
<db:term><db:link xlink:href="qt3d-animation-qmlmodule.xml" xlink:role="">Qt 3D Qt3DAnimation QML Types</db:link></db:term>
<db:listitem>
<db:para>Provides Qt 3D QML types for the animation module.</db:para>
</db:listitem>
</db:varlistentry>
<db:varlistentry>
<db:term><db:link xlink:href="qt3d-render-qmlmodule.xml" xlink:role="">Qt 3D Render QML Types</db:link></db:term>
<db:listitem>
<db:para>Provides Qt 3D QML types for rendering.</db:para>
</db:listitem>
</db:varlistentry>
<db:varlistentry>
<db:term><db:link xlink:href="qtquick-scene2d-qmlmodule.xml" xlink:role="">Qt 3D Scene2D QML Types</db:link></db:term>
<db:listitem>
<db:para>Provides Qt 3D QML types for the scene2d module.</db:para>
</db:listitem>
</db:varlistentry>
<db:varlistentry>
<db:term><db:link xlink:href="qtquick-scene3d-qmlmodule.xml" xlink:role="">Qt 3D Scene3D QML Types</db:link></db:term>
<db:listitem>
<db:para>Provides Qt 3D QML types for the Scene3D module.</db:para>
</db:listitem>
</db:varlistentry>
<db:varlistentry>
<db:term><db:link xlink:href="qt5compat-graphicaleffects-qmlmodule.xml" xlink:role="">Qt 5 Compatibility APIs: Graphical Effect QML Types</db:link></db:term>
<db:listitem>
<db:para>The Qt Graphical Effects module is provided for compatibility with applications written for Qt 5.</db:para>
</db:listitem>
</db:varlistentry>
<db:varlistentry>
<db:term><db:link xlink:href="qtcharts-qmlmodule.xml" xlink:role="">Qt Charts QML Types</db:link></db:term>
<db:listitem>
<db:para>QML types for the Qt Charts API.</db:para>
</db:listitem>
</db:varlistentry>
<db:varlistentry>
<db:term><db:link xlink:href="qtdatavisualization-qmlmodule.xml" xlink:role="">Qt Data Visualization QML Types</db:link></db:term>
<db:listitem>
<db:para>QML types for the Qt Data Visualization API.</db:para>
</db:listitem>
</db:varlistentry>
<db:varlistentry>
<db:term><db:link xlink:href="qt-labs-folderlistmodel-qmlmodule.xml" xlink:role="">Qt Labs FolderListModel QML Types</db:link></db:term>
<db:listitem>
<db:para>The FolderListModel provides a model of the contents of a file system folder.</db:para>
</db:listitem>
</db:varlistentry>
<db:varlistentry>
<db:term><db:link xlink:href="qt-labs-platform-qmlmodule.xml" xlink:role="">Qt Labs Platform QML Types</db:link></db:term>
<db:listitem>
<db:para>Provides QML types for native platform extensions.</db:para>
</db:listitem>
</db:varlistentry>
<db:varlistentry>
<db:term><db:link xlink:href="qt-labs-settings-qmlmodule.xml" xlink:role="">Qt Labs Settings QML Types</db:link></db:term>
<db:listitem>
<db:para>Provides persistent platform-independent application settings.</db:para>
</db:listitem>
</db:varlistentry>
<db:varlistentry>
<db:term><db:link xlink:href="qt-labs-wavefrontmesh-qmlmodule.xml" xlink:role="">Qt Labs WavefrontMesh QML Types</db:link></db:term>
<db:listitem>
<db:para>The WavefrontMesh provides a mesh based on a Wavefront .obj file.</db:para>
</db:listitem>
</db:varlistentry>
<db:varlistentry>
<db:term><db:link xlink:href="qt-labs-lottieqt-qmlmodule.xml" xlink:role="">Qt Lottie Animation QML Types</db:link></db:term>
<db:listitem>
<db:para>Provides QML types to display Bodymovin graphics and animations.</db:para>
</db:listitem>
</db:varlistentry>
<db:varlistentry>
<db:term><db:link xlink:href="qtmultimedia-qmlmodule.xml" xlink:role="">Qt Multimedia QML Types</db:link></db:term>
<db:listitem>
<db:para>Provides QML types for multimedia support.</db:para>
</db:listitem>
</db:varlistentry>
<db:varlistentry>
<db:term><db:link xlink:href="qtopcua-qmlmodule.xml" xlink:role="">Qt OPC UA QML Types</db:link></db:term>
<db:listitem>
<db:para>Provides QML types for Qt OPC UA.</db:para>
</db:listitem>
</db:varlistentry>
<db:varlistentry>
<db:term><db:link xlink:href="qtpositioning-qmlmodule.xml" xlink:role="">Qt Positioning QML Types</db:link></db:term>
<db:listitem>
<db:para>Provides QML types for position information.</db:para>
</db:listitem>
</db:varlistentry>
<db:varlistentry>
<db:term><db:link xlink:href="qtcore-qmlmodule.xml" xlink:role="">Qt QML Core QML Types</db:link></db:term>
<db:listitem>
<db:para>Provides core system functionality in QML.</db:para>
</db:listitem>
</db:varlistentry>
<db:varlistentry>
<db:term><db:link xlink:href="qtqml-models-qmlmodule.xml" xlink:role="">Qt QML Models QML Types</db:link></db:term>
<db:listitem>
<db:para>Provides QML types for data models</db:para>
</db:listitem>
</db:varlistentry>
<db:varlistentry>
<db:term><db:link xlink:href="qt-labs-qmlmodels-qmlmodule.xml" xlink:role="">Qt QML Models experimental QML Types</db:link></db:term>
<db:listitem>
<db:para>Provides QML experimental types for data models.</db:para>
</db:listitem>
</db:varlistentry>
<db:varlistentry>
<db:term><db:link xlink:href="qtqml-qmlmodule.xml" xlink:role="">Qt QML QML Types</db:link></db:term>
<db:listitem>
<db:para>List of QML types provided by the Qt QML module</db:para>
</db:listitem>
</db:varlistentry>
<db:varlistentry>
<db:term><db:link xlink:href="qtqml-workerscript-qmlmodule.xml" xlink:role="">Qt QML WorkerScript QML Types</db:link></db:term>
<db:listitem>
<db:para>Provides QML types for worker scripts.</db:para>
</db:listitem>
</db:varlistentry>
<db:varlistentry>
<db:term><db:link xlink:href="qtquick3d-assetutils-qmlmodule.xml" xlink:role="">Qt Quick 3D Asset Utility QML Types</db:link></db:term>
<db:listitem>
<db:para>Provides a way to load 3D assets directly from source at runtime.</db:para>
</db:listitem>
</db:varlistentry>
<db:varlistentry>
<db:term><db:link xlink:href="qtquick3d-effects-qmlmodule.xml" xlink:role="">Qt Quick 3D Effects QML Types</db:link></db:term>
<db:listitem>
<db:para>Provides QML types for the effects included in the Qt Quick 3D effect library.</db:para>
</db:listitem>
</db:varlistentry>
<db:varlistentry>
<db:term><db:link xlink:href="qtquick3d-helpers-qmlmodule.xml" xlink:role="">Qt Quick 3D Helpers QML Types</db:link></db:term>
<db:listitem>
<db:para>Module containing helpers for creating applications using Qt Quick 3D.</db:para>
</db:listitem>
</db:varlistentry>
<db:varlistentry>
<db:term><db:link xlink:href="qtquick3d-particles3d-qmlmodule.xml" xlink:role="">Qt Quick 3D Particles3D QML Types</db:link></db:term>
<db:listitem>
<db:para>Module containing Particles for the Qt Quick 3D.</db:para>
</db:listitem>
</db:varlistentry>
<db:varlistentry>
<db:term><db:link xlink:href="qtquick3dphysics-qmlmodule.xml" xlink:role="">Qt Quick 3D Physics QML Types</db:link></db:term>
<db:listitem>
<db:para>Provides the QML types to include physics items into a Qt Quick scene.</db:para>
</db:listitem>
</db:varlistentry>
<db:varlistentry>
<db:term><db:link xlink:href="qtquick3d-qmlmodule.xml" xlink:role="">Qt Quick 3D QML Types</db:link></db:term>
<db:listitem>
<db:para>Provides the QML types to include 3D items into a Qt Quick scene.</db:para>
</db:listitem>
</db:varlistentry>
<db:varlistentry>
<db:term><db:link xlink:href="qtquick-controls2-qmlmodule.xml" xlink:role="">Qt Quick Controls QML Types</db:link></db:term>
<db:listitem>
<db:para>Provides QML types for user interfaces (Qt Quick Controls).</db:para>
</db:listitem>
</db:varlistentry>
<db:varlistentry>
<db:term><db:link xlink:href="qtquick-dialogs-qmlmodule.xml" xlink:role="">Qt Quick Dialogs QML Types</db:link></db:term>
<db:listitem>
<db:para>Provides QML types for creating and interacting with system dialogs.</db:para>
</db:listitem>
</db:varlistentry>
<db:varlistentry>
<db:term><db:link xlink:href="qtquick-layouts-qmlmodule.xml" xlink:role="">Qt Quick Layouts QML Types</db:link></db:term>
<db:listitem>
<db:para>Provides QML types for arranging QML items in a user interface.</db:para>
</db:listitem>
</db:varlistentry>
<db:varlistentry>
<db:term><db:link xlink:href="qtquick-localstorage-qmlmodule.xml" xlink:role="">Qt Quick Local Storage QML Types</db:link></db:term>
<db:listitem>
<db:para>Provides a JavaScript object singleton type for accessing a local SQLite database</db:para>
</db:listitem>
</db:varlistentry>
<db:varlistentry>
<db:term><db:link xlink:href="qtquick-pdf-qmlmodule.xml" xlink:role="">Qt Quick PDF QML Types</db:link></db:term>
<db:listitem>
<db:para>Provides QML types for handling PDF documents.</db:para>
</db:listitem>
</db:varlistentry>
<db:varlistentry>
<db:term><db:link xlink:href="qtquick-particles-qmlmodule.xml" xlink:role="">Qt Quick Particles QML Types</db:link></db:term>
<db:listitem>
<db:para>Provides QML types for particle effects</db:para>
</db:listitem>
</db:varlistentry>
<db:varlistentry>
<db:term><db:link xlink:href="qtquick-qmlmodule.xml" xlink:role="">Qt Quick QML Types</db:link></db:term>
<db:listitem>
<db:para>Provides graphical QML types.</db:para>
</db:listitem>
</db:varlistentry>
<db:varlistentry>
<db:term><db:link xlink:href="qtquick-shapes-qmlmodule.xml" xlink:role="">Qt Quick Shapes QML Types</db:link></db:term>
<db:listitem>
<db:para>Provides QML types for drawing stroked and filled shapes.</db:para>
</db:listitem>
</db:varlistentry>
<db:varlistentry>
<db:term><db:link xlink:href="qt-labs-sharedimage-qmlmodule.xml" xlink:role="">Qt Quick Shared Image Provider</db:link></db:term>
<db:listitem>
<db:para>Adds an image provider which utilizes shared CPU memory</db:para>
</db:listitem>
</db:varlistentry>
<db:varlistentry>
<db:term><db:link xlink:href="qtquick-templates2-qmlmodule.xml" xlink:role="">Qt Quick Templates 2 QML Types</db:link></db:term>
<db:listitem>
<db:para>Provides QML types for templates (Qt Quick Templates).</db:para>
</db:listitem>
</db:varlistentry>
<db:varlistentry>
<db:term><db:link xlink:href="qttest-qmlmodule.xml" xlink:role="">Qt Quick Test QML Types</db:link></db:term>
<db:listitem>
<db:para>Provides QML types to unit test your QML application.</db:para>
</db:listitem>
</db:varlistentry>
<db:varlistentry>
<db:term><db:link xlink:href="qtquick-timeline-qmlmodule.xml" xlink:role="">Qt Quick Timeline QML Types</db:link></db:term>
<db:listitem>
<db:para>Provides QML types to use timelines and keyframes to animate Qt Quick user interfaces.</db:para>
</db:listitem>
</db:varlistentry>
<db:varlistentry>
<db:term><db:link xlink:href="qtquick-virtualkeyboard-components-qmlmodule.xml" xlink:role="">Qt Quick Virtual Keyboard Components QML Types</db:link></db:term>
<db:listitem>
<db:para>Provides QML types for customizing virtual keyboard layouts.</db:para>
</db:listitem>
</db:varlistentry>
<db:varlistentry>
<db:term><db:link xlink:href="qtquick-virtualkeyboard-settings-qmlmodule.xml" xlink:role="">Qt Quick Virtual Keyboard Settings QML Types</db:link></db:term>
<db:listitem>
<db:para>Provides settings for Qt Virtual Keyboard.</db:para>
</db:listitem>
</db:varlistentry>
<db:varlistentry>
<db:term><db:link xlink:href="qtquick-virtualkeyboard-styles-qmlmodule.xml" xlink:role="">Qt Quick Virtual Keyboard Styles QML Types</db:link></db:term>
<db:listitem>
<db:para>Provides styling for Qt Virtual Keyboard.</db:para>
</db:listitem>
</db:varlistentry>
<db:varlistentry>
<db:term><db:link xlink:href="qt-labs-animation-qmlmodule.xml" xlink:role="">Qt Quick experimental animation types</db:link></db:term>
<db:listitem>
<db:para>Provides QML experimental types for animation</db:para>
</db:listitem>
</db:varlistentry>
<db:varlistentry>
<db:term><db:link xlink:href="qtremoteobjects-qmlmodule.xml" xlink:role="">Qt Remote Objects QML Types</db:link></db:term>
<db:listitem>
<db:para>Provides QML types for remote objects support.</db:para>
</db:listitem>
</db:varlistentry>
<db:varlistentry>
<db:term><db:link xlink:href="qtscxml-qmlmodule.xml" xlink:role="">Qt SCXML QML Types</db:link></db:term>
<db:listitem>
<db:para>Enables the use of SCXML state machines with QML.</db:para>
</db:listitem>
</db:varlistentry>
<db:varlistentry>
<db:term><db:link xlink:href="qtsensors-qmlmodule.xml" xlink:role="">Qt Sensors QML Types</db:link></db:term>
<db:listitem>
<db:para>Provides QML types for reading sensor data.</db:para>
</db:listitem>
</db:varlistentry>
<db:varlistentry>
<db:term><db:link xlink:href="qtquick3d-spatialaudio-qmlmodule.xml" xlink:role="">Qt Spatial Audio QML Types</db:link></db:term>
<db:listitem>
<db:para>Provides QML types for spatial audio.</db:para>
</db:listitem>
</db:varlistentry>
<db:varlistentry>
<db:term><db:link xlink:href="qtqml-statemachine-qmlmodule.xml" xlink:role="">Qt State Machine QML Types</db:link></db:term>
<db:listitem>
<db:para>Enables the use of State Machine with QML.</db:para>
</db:listitem>
</db:varlistentry>
<db:varlistentry>
<db:term><db:link xlink:href="qttexttospeech-qmlmodule.xml" xlink:role="">Qt TextToSpeech QML Types</db:link></db:term>
<db:listitem>
<db:para>provides QML types to access text-to-speech functionality.</db:para>
</db:listitem>
</db:varlistentry>
<db:varlistentry>
<db:term><db:link xlink:href="qtquick-virtualkeyboard-qmlmodule.xml" xlink:role="">Qt Virtual Keyboard Module QML Types</db:link></db:term>
<db:listitem>
<db:para>Provides QML types for the virtual keyboard.</db:para>
</db:listitem>
</db:varlistentry>
<db:varlistentry>
<db:term><db:link xlink:href="qtwayland-compositor-qmlmodule.xml" xlink:role="">Qt Wayland Compositor QML Types</db:link></db:term>
<db:listitem>
<db:para>Provides QML types for writing custom Wayland display servers.</db:para>
</db:listitem>
</db:varlistentry>
<db:varlistentry>
<db:term><db:link xlink:href="qtwayland-compositor-iviapplication-qmlmodule.xml" xlink:role="">Qt Wayland IviApplication Extension</db:link></db:term>
<db:listitem>
<db:para>Provides a Qt API for the IviApplication shell extension.</db:para>
</db:listitem>
</db:varlistentry>
<db:varlistentry>
<db:term><db:link xlink:href="qtwayland-compositor-presentationtime-qmlmodule.xml" xlink:role="">Qt Wayland Presentation Time Extension</db:link></db:term>
<db:listitem>
<db:para>Provides tracking the timing when a frame is presented on screen.</db:para>
</db:listitem>
</db:varlistentry>
<db:varlistentry>
<db:term><db:link xlink:href="qtwayland-compositor-qtshell-qmlmodule.xml" xlink:role="">Qt Wayland Qt Shell Extension</db:link></db:term>
<db:listitem>
<db:para>Provides a shell extension for Qt applications running on a Qt Wayland Compositor.</db:para>
</db:listitem>
</db:varlistentry>
<db:varlistentry>
<db:term><db:link xlink:href="qtwayland-compositor-wlshell-qmlmodule.xml" xlink:role="">Qt Wayland WlShell extension</db:link></db:term>
<db:listitem>
<db:para>Provides a Qt API for the WlShell extension.</db:para>
</db:listitem>
</db:varlistentry>
<db:varlistentry>
<db:term><db:link xlink:href="qtwayland-compositor-xdgshell-qmlmodule.xml" xlink:role="">Qt Wayland XdgShell Extension</db:link></db:term>
<db:listitem>
<db:para>Provides a Qt API for the XdgShell shell extension.</db:para>
</db:listitem>
</db:varlistentry>
<db:varlistentry>
<db:term><db:link xlink:href="qtwebchannel-qmlmodule.xml" xlink:role="">Qt WebChannel QML Types</db:link></db:term>
<db:listitem>
<db:para>List of QML types that provide WebChannel functionality.</db:para>
</db:listitem>
</db:varlistentry>
<db:varlistentry>
<db:term><db:link xlink:href="qtwebengine-qmlmodule.xml" xlink:role="">Qt WebEngine QML Types</db:link></db:term>
<db:listitem>
<db:para>Provides QML types for rendering web content within a QML application.</db:para>
</db:listitem>
</db:varlistentry>
<db:varlistentry>
<db:term><db:link xlink:href="qtwebsockets-qmlmodule.xml" xlink:role="">Qt WebSockets QML Types</db:link></db:term>
<db:listitem>
<db:para>Provides QML types for WebSocket-based communication.</db:para>
</db:listitem>
</db:varlistentry>
<db:varlistentry>
<db:term><db:link xlink:href="qtwebview-qmlmodule.xml" xlink:role="">Qt WebView QML Types</db:link></db:term>
<db:listitem>
<db:para>Provides QML types for Qt WebView.</db:para>
</db:listitem>
</db:varlistentry>
<db:varlistentry>
<db:term><db:link xlink:href="qtqml-xmllistmodel-qmlmodule.xml" xlink:role="">Qt XmlListModel QML Types</db:link></db:term>
<db:listitem>
<db:para>Provides QML types for creating models from XML data</db:para>
</db:listitem>
</db:varlistentry>
<db:varlistentry>
<db:term><db:link xlink:href="qtquick3d-audio-qmlmodule.xml" xlink:role="">QtQuick3D.SpatialAudio QML Types</db:link></db:term>
<db:listitem>
<db:para>Provides QML types for spatial audio in Qt Quick 3D.</db:para>
</db:listitem>
</db:varlistentry>
</db:variablelist>
</db:article>
