<?xml version="1.0" encoding="UTF-8"?>
<db:article xmlns:db="http://docbook.org/ns/docbook" xmlns:xlink="http://www.w3.org/1999/xlink" version="5.2" xml:lang="en">
<db:info>
<db:title>QAnimationClip Class</db:title>
<db:subtitle>Qt3DAnimation::QAnimationClip</db:subtitle>
<db:productname>Qt3D</db:productname>
<db:edition>Qt 6.5.3 Reference Documentation</db:edition>
<db:titleabbrev>Qt 3D Reference Documentation</db:titleabbrev>
<db:abstract>
<db:para>Specifies key frame animation data.</db:para>
</db:abstract>
<db:pubdate>2024-02-14</db:pubdate>
<db:date>2024-02-14</db:date>
<db:authorgroup>
<db:author>
<db:orgname class="corporation">The Qt Company Ltd.</db:orgname>
</db:author>
</db:authorgroup>
</db:info>
<db:variablelist>
<db:varlistentry>
<db:term>Header</db:term>
<db:listitem>
<db:para>QAnimationClip</db:para>
</db:listitem>
</db:varlistentry>
<db:varlistentry>
<db:term>CMake</db:term>
<db:listitem>
<db:para>find_package(Qt6 REQUIRED COMPONENTS 3danimation)</db:para>
<db:para>target_link_libraries(mytarget PRIVATE Qt6::3danimation)</db:para>
</db:listitem>
</db:varlistentry>
<db:varlistentry>
<db:term>qmake</db:term>
<db:listitem>
<db:para>QT += 3danimation</db:para>
</db:listitem>
</db:varlistentry>
<db:varlistentry>
<db:term>Inherits</db:term>
<db:listitem>
<db:para><db:link xlink:href="qt3danimation-qabstractanimationclip.xml" xlink:role="class">Qt3DAnimation::QAbstractAnimationClip</db:link></db:para>
</db:listitem>
</db:varlistentry>
</db:variablelist>
<db:section xml:id="details">
<db:title>Detailed Description</db:title>
</db:section>
<db:section xml:id="member-function-documentation">
<db:title>Member Function Documentation</db:title>
<db:section xml:id="clipData">
<db:title>Qt3DAnimation::QAnimationClipData QAnimationClip::clipData() const</db:title>
<db:methodsynopsis>
<db:modifier>const</db:modifier>
<db:type>Qt3DAnimation::QAnimationClipData</db:type>
<db:methodname>clipData</db:methodname>
<db:void/>
<db:synopsisinfo role="meta">plain</db:synopsisinfo>
<db:synopsisinfo role="associated-property">clipData</db:synopsisinfo>
<db:synopsisinfo role="signature">Qt3DAnimation::QAnimationClipData clipData() const</db:synopsisinfo>
<db:synopsisinfo role="access">public</db:synopsisinfo>
<db:synopsisinfo role="status">active</db:synopsisinfo>
<db:synopsisinfo role="threadsafeness">unspecified</db:synopsisinfo>
</db:methodsynopsis>
<db:para>Returns the data describing the animation clip.</db:para>
<db:note>
<db:para>Getter function for property clipData. </db:para>
</db:note>
<db:section>
<db:title>See Also</db:title>
<db:para><db:emphasis>See also </db:emphasis>
<db:simplelist type="vert" role="see-also">
<db:member><db:link xlink:href="qt3danimation-qanimationclip.xml#setClipData">setClipData</db:link>()</db:member>
</db:simplelist>
</db:para>
</db:section>
</db:section>
<db:section xml:id="setClipData">
<db:title>void QAnimationClip::setClipData(const Qt3DAnimation::QAnimationClipData &amp;<db:emphasis>clipData</db:emphasis>)</db:title>
<db:methodsynopsis>
<db:void/>
<db:methodname>setClipData</db:methodname>
<db:methodparam>
<db:type>const Qt3DAnimation::QAnimationClipData &amp;</db:type>
<db:parameter>clipData</db:parameter>
</db:methodparam>
<db:synopsisinfo role="meta">plain</db:synopsisinfo>
<db:synopsisinfo role="associated-property">clipData</db:synopsisinfo>
<db:synopsisinfo role="signature">void setClipData(const Qt3DAnimation::QAnimationClipData &amp;clipData)</db:synopsisinfo>
<db:synopsisinfo role="access">public</db:synopsisinfo>
<db:synopsisinfo role="status">active</db:synopsisinfo>
<db:synopsisinfo role="threadsafeness">unspecified</db:synopsisinfo>
</db:methodsynopsis>
<db:para>Set the parameters of the clip according to the <db:code role="parameter">clipData</db:code> provided.</db:para>
<db:note>
<db:para>Setter function for property clipData. </db:para>
</db:note>
<db:section>
<db:title>See Also</db:title>
<db:para><db:emphasis>See also </db:emphasis>
<db:simplelist type="vert" role="see-also">
<db:member><db:link xlink:href="qt3danimation-qanimationclip.xml#clipData">clipData</db:link>()</db:member>
</db:simplelist>
</db:para>
</db:section>
</db:section>
</db:section>
</db:article>
