<?xml version="1.0" encoding="UTF-8"?>
<db:article xmlns:db="http://docbook.org/ns/docbook" xmlns:xlink="http://www.w3.org/1999/xlink" version="5.2" xml:lang="en">
<db:info>
<db:title>Qt Quick Examples - Touch Interaction</db:title>
<db:productname>QtQuick</db:productname>
<db:edition>Qt 5.6.3 Reference Documentation</db:edition>
<db:titleabbrev>Qt Quick Reference Documentation</db:titleabbrev>
<db:abstract>
<db:para>A collection of QML Touch Interaction examples.</db:para>
</db:abstract>
<db:pubdate>2025-06-29</db:pubdate>
<db:date>2025-06-29</db:date>
<db:authorgroup>
<db:author>
<db:orgname class="corporation">The Qt Company Ltd.</db:orgname>
</db:author>
</db:authorgroup>
</db:info>
<db:programlisting language="cpp">&lt;RCC&gt;
    &lt;qresource prefix=&quot;/touchinteraction&quot;&gt;
        &lt;file&gt;touchinteraction.qml&lt;/file&gt;
        &lt;file&gt;flickable/basic-flickable.qml&lt;/file&gt;
        &lt;file&gt;flickable/corkboards.qml&lt;/file&gt;
        &lt;file&gt;flickable/content/cork.jpg&lt;/file&gt;
        &lt;file&gt;flickable/content/note-yellow.png&lt;/file&gt;
        &lt;file&gt;flickable/content/Panel.qml&lt;/file&gt;
        &lt;file&gt;flickable/content/tack.png&lt;/file&gt;
        &lt;file&gt;multipointtouch/bearwhack.qml&lt;/file&gt;
        &lt;file&gt;multipointtouch/multiflame.qml&lt;/file&gt;
        &lt;file&gt;multipointtouch/content/AugmentedTouchPoint.qml&lt;/file&gt;
        &lt;file&gt;multipointtouch/content/Bear0.png&lt;/file&gt;
        &lt;file&gt;multipointtouch/content/Bear1.png&lt;/file&gt;
        &lt;file&gt;multipointtouch/content/Bear2.png&lt;/file&gt;
        &lt;file&gt;multipointtouch/content/Bear3.png&lt;/file&gt;
        &lt;file&gt;multipointtouch/content/BearB.png&lt;/file&gt;
        &lt;file&gt;multipointtouch/content/BearWhackParticleSystem.qml&lt;/file&gt;
        &lt;file&gt;multipointtouch/content/blur-circle.png&lt;/file&gt;
        &lt;file&gt;multipointtouch/content/blur-circle3.png&lt;/file&gt;
        &lt;file&gt;multipointtouch/content/heart-blur.png&lt;/file&gt;
        &lt;file&gt;multipointtouch/content/ParticleFlame.qml&lt;/file&gt;
        &lt;file&gt;multipointtouch/content/title.png&lt;/file&gt;
        &lt;file&gt;pincharea/flickresize.qml&lt;/file&gt;
        &lt;file&gt;pincharea/qt-logo.jpg&lt;/file&gt;
    &lt;/qresource&gt;
&lt;/RCC&gt;

</db:programlisting>
</db:article>
